DesignSpark.ESDK-23.2.1-py3.10-nspkg.pth
DesignSpark/ESDK/AppLogger.py
DesignSpark/ESDK/CO2.py
DesignSpark/ESDK/DFRobot_SGP40_VOCAlgorithm.py
DesignSpark/ESDK/FDH.py
DesignSpark/ESDK/MAIN.py
DesignSpark/ESDK/NO2.py
DesignSpark/ESDK/NRD.py
DesignSpark/ESDK/PM2.py
DesignSpark/ESDK/THV.py
DesignSpark/ESDK/__init__.py
DesignSpark.ESDK-23.2.1.dist-info/LICENSE.rst
DesignSpark.ESDK-23.2.1.dist-info/METADATA
DesignSpark.ESDK-23.2.1.dist-info/WHEEL
DesignSpark.ESDK-23.2.1.dist-info/namespace_packages.txt
DesignSpark.ESDK-23.2.1.dist-info/top_level.txt
DesignSpark.ESDK-23.2.1.dist-info/RECORD
