Metadata-Version: 2.1
Name: DesignSpark.ESDK
Version: 23.2.1
Summary: DesignSpark ESDK support library
Home-page: https://github.com/designsparkrs/DesignSpark.ESDK
Author: RS Components
Author-email: maint@abopen.com
License: MIT License
Keywords: raspberry pi raspi designspark esdk
Classifier: Development Status :: 3 - Alpha
Classifier: Intended Audience :: Developers
Classifier: License :: OSI Approved :: MIT License
Classifier: Operating System :: POSIX :: Linux
Classifier: Programming Language :: Python :: 3
Classifier: Programming Language :: Python :: 3.7
Classifier: Topic :: Education
Classifier: Topic :: System :: Hardware
Classifier: Topic :: System :: Hardware :: Hardware Drivers
License-File: LICENSE.rst
Requires-Dist: smbus2
Requires-Dist: toml
Requires-Dist: python-geohash
Requires-Dist: gpsdclient
Requires-Dist: paho-mqtt
Requires-Dist: requests
Requires-Dist: python-snappy
Requires-Dist: RPi.GPIO
